MANIFEST.in
NEWS.txt
README.rst
setup.py
src/jsautobuild/__init__.py
src/jsautobuild.egg-info/PKG-INFO
src/jsautobuild.egg-info/SOURCES.txt
src/jsautobuild.egg-info/dependency_links.txt
src/jsautobuild.egg-info/entry_points.txt
src/jsautobuild.egg-info/not-zip-safe
src/jsautobuild.egg-info/requires.txt
src/jsautobuild.egg-info/top_level.txt