Metadata-Version: 1.0
Name: jsautobuild
Version: 0.2
Summary: Auto build JS files using Pyinotify to help during development of JS in projects
Home-page: UNKNOWN
Author: Rick Harding
Author-email: rharding@canonical.com
License: BSD
Keywords: javascript yui build minify development
Platform: UNKNOWN
